src/daikin_one/__init__.py
src/daikin_one/api_contracts.py
src/daikin_one/daikin_one.py
pydaikinone-0.0.2.dist-info/METADATA
pydaikinone-0.0.2.dist-info/WHEEL
pydaikinone-0.0.2.dist-info/licenses/LICENSE
pydaikinone-0.0.2.dist-info/RECORD
